arduino_board_collection/__init__.py
arduino_board_collection/board_collection.py
arduino_board_collection/create_board.py
arduino_board_collection/boards/__init__.py
arduino_board_collection/boards/controller_boards/__init__.py
arduino_board_collection/boards/controller_boards/basic/__init__.py
arduino_board_collection/boards/controller_boards/motors/__init__.py
arduino_board_collection/boards/controller_boards/motors/AccelStepperBoard/__init__.py
arduino_board_collection/boards/controller_boards/motors/AccelStepperBoard/board.py
arduino_board_collection/boards/sensor_boards/__init__.py
arduino_board_collection/boards/sensor_boards/basic/__init__.py
arduino_board_collection/boards/sensor_boards/basic/analog_read_board/__init__.py
arduino_board_collection/boards/sensor_boards/basic/analog_read_board/board.py
arduino_board_collection/boards/sensor_boards/basic/bush_button/__init__.py
arduino_board_collection/boards/sensor_boards/basic/bush_button/board.py
arduino_board_collection/boards/sensor_boards/basic/hx711_board/__init__.py
arduino_board_collection/boards/sensor_boards/basic/hx711_board/board.py
arduino_board_collection/boards/sensor_boards/basic/serial_peripheral_interface/__init__.py
arduino_board_collection/boards/sensor_boards/basic/serial_peripheral_interface/board.py
arduino_board_collection/boards/sensor_boards/force/__init__.py
arduino_board_collection/boards/sensor_boards/force/tesile_test_board/__init__.py
arduino_board_collection/boards/sensor_boards/force/tesile_test_board/tesile_test_board.py
arduino_board_collection/boards/sensor_boards/thermal/__init__.py
arduino_board_collection/boards/sensor_boards/thermal/max6675/__init__.py
arduino_board_collection/boards/sensor_boards/thermal/max6675/board.py
arduino_board_collection/boards/sensor_boards/thermal/thermistor/__init__.py
arduino_board_collection/boards/sensor_boards/thermal/thermistor/board.py
arduino_board_collection/boards/sensor_signal_boards/__init__.py
ArduinoBoardCollection-0.1.1566386412.dist-info/METADATA
ArduinoBoardCollection-0.1.1566386412.dist-info/WHEEL
ArduinoBoardCollection-0.1.1566386412.dist-info/top_level.txt
ArduinoBoardCollection-0.1.1566386412.dist-info/RECORD
