Metadata-Version: 2.1
Name: ArduinoBoardCollection
Version: 0.1.1566386412
Summary: Some boards for ArduinoController
Home-page: https://github.com/JulianKimmig/arduino_board_collection
Author: Julian Kimmig
Author-email: julian-kimmig@gmx.net
License: UNKNOWN
Platform: UNKNOWN
Classifier: Programming Language :: Python :: 3
Classifier: License :: OSI Approved :: MIT License
Classifier: Operating System :: OS Independent
Requires-Dist: ArduinoController
